Metadata-Version: 1.0
Name: matrix-pack
Version: 0.1
Summary: matrix operations
Home-page: UNKNOWN
Author: UNKNOWN
Author-email: UNKNOWN
License: UNKNOWN
Platform: UNKNOWN
